Workbook

Sheet ReadMe
A1: Burundi CGE backcast: minimum data request, 2019-2024
A3: What to fill
A4: Sheet 'Data': the yellow cells only, one value per year. Leave a cell empty if the figure does not exist; do not estimate.
A5: Also fill, for each row, 'Source used' (table and edition) and any note.
A6: Fill the three cells at the top of 'Data': source, base year of constant prices, and currency unit.
A8: Block A: national accounts (22 cells per year)
A9: Eleven series, each at CURRENT prices and at CONSTANT prices. All rows must come from the same source and vintage, on the rebased basis.
A10: Current prices: billions of BIF. Constant prices: billions of BIF at the prices of the base year you record at the top.
A11: If only growth rates are published for constant prices, enter the constant-price level for the base year and the published levels or cumulated index; say which in the Notes column.
A13: Block B: foreign exchange at the official rate (2 cells per year)
A14: USD millions of imports paid with foreign exchange sold by BRB at the official rate, total and of which petroleum products.
A16: Why only these
... A20: Sheet 'Checks' computes deflators, shares and the GDP identity from what you enter. Use it to spot typos; do not edit it.

Sheet Data
A1: Source used for block A (publication, table, edition) | E1: INSBU (Institut National de la Statistique du Burundi): Tableaux ressources-emplois 2016-2024 at current and previous-year prices; TCEI 2021, 2023, 2024. Files in 'raw data (kodzovi)', received 2026-09-29.
A2: Base year of constant prices | E2: 2019, chain-linked (INSBU constant tables are at previous-year prices)
A3: Currency unit (e.g. BIF billions) | E3: BIF billions (INSBU files are in BIF millions)
A5: ID | B5: Block | C5: Variable | D5: Prices | E5: Unit | F5: 2019 | G5: 2020 | H5: 2021 | I5: 2022 | J5: 2023 | K5: 2024 | L5: Ideal source | M5: Why it is needed | N5: Source used | O5: Notes
A6: GDP_CP | B6: A. National accounts | C6: Gross domestic product, market prices | D6: current | E6: BIF billions | F6: 9231.9 | G6: 9941.8 | H6: 10816.4 | I6: 12790 | J6: 15835.4 | K6: 20058 | L6: ISTEEBU rebased national accounts (the series behind the WDI rebased GDP), or IMF staff report CR 26/150 statistical tables. Use ONE source for every row in block A. | M6: Settles which nominal GDP and deflator are right: the workbook's rebased GDP deflator rises 2.06x over 2019-24, MFMod's only 1.65x. | N6: INSBU TRE, current prices (TRE COURANT yyyy.xls)
A7: GDP_KP | B7: A. National accounts | C7: Gross domestic product, market prices | D7: constant | E7: BIF billions, base-year prices | F7: 9231.9 | G7: 9241.8 | H7: 9457.8 | I7: 9580.7 | J7: 9805.1 | K7: 10302.6 | L7: ISTEEBU rebased national accounts (the series behind the WDI rebased GDP), or IMF staff report CR 26/150 statistical tables. Use ONE source for every row in block A. | M7: Settles which nominal GDP and deflator are right: the workbook's rebased GDP deflator rises 2.06x over 2019-24, MFMod's only 1.65x. | N7: INSBU TRE, previous-year prices (TRE CONSTANT yyyy.xls), chain-linked to 2019 prices
A8: PRVC_CP | B8: A. National accounts | C8: Private final consumption | D8: current | E8: BIF billions | F8: 8499.1 | G8: 9047.5 | H8: 9717.2 | I8: 11664.6 | J8: 14994.8 | K8: 18191.7 | L8: ISTEEBU rebased national accounts (the series behind the WDI rebased GDP), or IMF staff report CR 26/150 statistical tables. Use ONE source for every row in block A. | M8: Real growth is a validation target; current/constant gives its deflator. | N8: INSBU TRE, current prices (TRE COURANT yyyy.xls) | O8: Households (own-account + marketed) plus NPISH, as in most national-accounts presentations; households alone are ~97% of it.
A9: PRVC_KP | B9: A. National accounts | C9: Private final consumption | D9: constant | E9: BIF billions, base-year prices | F9: 8499.1 | G9: 8396.1 | H9: 8609.7 | I9: 8856.8 | J9: 9427.1 | K9: 9612.9 | L9: ISTEEBU rebased national accounts (the series behind the WDI rebased GDP), or IMF staff report CR 26/150 statistical tables. Use ONE source for every row in block A. | M9: Real growth is a validation target; current/constant gives its deflator. | N9: INSBU TRE, previous-year prices (TRE CONSTANT yyyy.xls), chain-linked to 2019 prices | O9: Households (own-account + marketed) plus NPISH, as in most national-accounts presentations; households alone are ~97% of it.
A10: GOVC_CP | B10: A. National accounts | C10: Government final consumption | D10: current | E10: BIF billions | F10: 980.3 | G10: 1044.7 | H10: 1093.8 | I10: 1225.2 | J10: 1335.2 | K10: 1503.2 | L10: ISTEEBU rebased national accounts (the series behind the WDI rebased GDP), or IMF staff report CR 26/150 statistical tables. Use ONE source for every row in block A. | M10: Drives the government-consumption path. The two sources in the old workbook disagree on its level and direction. | N10: INSBU TRE, current prices (TRE COURANT yyyy.xls)
A11: GOVC_KP | B11: A. National accounts | C11: Government final consumption | D11: constant | E11: BIF billions, base-year prices | F11: 980.3 | G11: 1003.8 | H11: 1034.9 | I11: 993.6 | J11: 1007.6 | K11: 1035.7 | L11: ISTEEBU rebased national accounts (the series behind the WDI rebased GDP), or IMF staff report CR 26/150 statistical tables. Use ONE source for every row in block A. | M11: Drives the government-consumption path. The two sources in the old workbook disagree on its level and direction. | N11: INSBU TRE, previous-year prices (TRE CONSTANT yyyy.xls), chain-linked to 2019 prices
A12: GFCF_CP | B12: A. National accounts | C12: Gross fixed capital formation, total | D12: current | E12: BIF billions | F12: 1044.7 | G12: 1050.7 | H12: 1387.3 | I12: 1534.7 | J12: 1840.9 | K12: 2429.6 | L12: ISTEEBU rebased national accounts (the series behind the WDI rebased GDP), or IMF staff report CR 26/150 statistical tables. Use ONE source for every row in block A. | M12: Model investment overshoots by ~2.8 pts/yr; needs a consistent real series. | N12: INSBU TRE, current prices (TRE COURANT yyyy.xls) | O12: Excludes change in inventories, which rose from 0.3% of GDP in 2019 to 2.4-4.4% in 2020-24 (TRE).
A13: GFCF_KP | B13: A. National accounts | C13: Gross fixed capital formation, total | D13: constant | E13: BIF billions, base-year prices | F13: 1044.7 | G13: 995.4 | H13: 1177.8 | I13: 1195.8 | J13: 1265.9 | K13: 1292.1 | L13: ISTEEBU rebased national accounts (the series behind the WDI rebased GDP), or IMF staff report CR 26/150 statistical tables. Use ONE source for every row in block A. | M13: Model investment overshoots by ~2.8 pts/yr; needs a consistent real series. | N13: INSBU TRE, previous-year prices (TRE CONSTANT yyyy.xls), chain-linked to 2019 prices | O13: Excludes change in inventories, which rose from 0.3% of GDP in 2019 to 2.4-4.4% in 2020-24 (TRE).
A14: GFCFG_CP | B14: A. National accounts | C14: of which: public gross fixed capital formation | D14: current | E14: BIF billions | H14: 566.5 | J14: 1253.3 | K14: 1730.7 | L14: ISTEEBU rebased national accounts (the series behind the WDI rebased GDP), or IMF staff report CR 26/150 statistical tables. Use ONE source for every row in block A. | M14: Feeds the government investment path; the old workbook's 4.0% of GDP does not match MFMod's 10.3% capital expenditure. | N14: INSBU TCEI (TCEI2021_VF, TCE_2023_BANGA_IMCSVF, TCEI2024_VF), P51 APU | O14: TCEI P51 of general government (APU). Only 2021, 2023, 2024 exist. The 2021 split between government and non-financial corporations (5.2% / 5.3% of GDP) differs sharply from 2023-24 (7.9-8.6% / 0.9-1.0%): probable reclassification, to confirm with INSBU.
A15: GFCFG_KP | B15: A. National accounts | C15: of which: public gross fixed capital formation | D15: constant | E15: BIF billions, base-year prices | L15: ISTEEBU rebased national accounts (the series behind the WDI rebased GDP), or IMF staff report CR 26/150 statistical tables. Use ONE source for every row in block A. | M15: Feeds the government investment path; the old workbook's 4.0% of GDP does not match MFMod's 10.3% capital expenditure. | O15: No volume series in the INSBU files.
A16: EXP_CP | B16: A. National accounts | C16: Exports of goods and services | D16: current | E16: BIF billions | F16: 552.1 | G16: 519.8 | H16: 598.2 | I16: 672.8 | J16: 973.6 | K16: 1002.4 | L16: ISTEEBU rebased national accounts (the series behind the WDI rebased GDP), or IMF staff report CR 26/150 statistical tables. Use ONE source for every row in block A. | M16: Real exports are pinned; current/constant gives the realised export price. | N16: INSBU TRE, current prices (TRE COURANT yyyy.xls)
A17: EXP_KP | B17: A. National accounts | C17: Exports of goods and services | D17: constant | E17: BIF billions, base-year prices | F17: 552.1 | G17: 522.1 | H17: 518.8 | I17: 469.5 | J17: 524.3 | K17: 512.2 | L17: ISTEEBU rebased national accounts (the series behind the WDI rebased GDP), or IMF staff report CR 26/150 statistical tables. Use ONE source for every row in block A. | M17: Real exports are pinned; current/constant gives the realised export price. | N17: INSBU TRE, previous-year prices (TRE CONSTANT yyyy.xls), chain-linked to 2019 prices
A18: IMP_CP | B18: A. National accounts | C18: Imports of goods and services | D18: current | E18: BIF billions | F18: 1874.5 | G18: 1964.7 | H18: 2304.5 | I18: 2870.4 | J18: 3688.7 | K18: 3837.9 | L18: ISTEEBU rebased national accounts (the series behind the WDI rebased GDP), or IMF staff report CR 26/150 statistical tables. Use ONE source for every row in block A. | M18: Main remaining gap. Current/constant gives the realised import price and a trade share consistent with the GDP above. | N18: INSBU TRE, current prices (TRE COURANT yyyy.xls)
A19: IMP_KP | B19: A. National accounts | C19: Imports of goods and services | D19: constant | E19: BIF billions, base-year prices | F19: 1874.5 | G19: 1899.6 | H19: 2158.4 | I19: 2356.3 | J19: 2685.1 | K19: 2413.3 | L19: ISTEEBU rebased national accounts (the series behind the WDI rebased GDP), or IMF staff report CR 26/150 statistical tables. Use ONE source for every row in block A. | M19: Main remaining gap. Current/constant gives the realised import price and a trade share consistent with the GDP above. | N19: INSBU TRE, previous-year prices (TRE CONSTANT yyyy.xls), chain-linked to 2019 prices
A20: VAAGR_CP | B20: A. National accounts | C20: Value added: agriculture, forestry, fishing (ISIC A) | D20: current | E20: BIF billions | F20: 3459.6 | G20: 3984.6 | H20: 4233.7 | I20: 5250.9 | J20: 6828.6 | K20: 8113.8 | L20: ISTEEBU rebased national accounts (the series behind the WDI rebased GDP), or IMF staff report CR 26/150 statistical tables. Use ONE source for every row in block A. | M20: Sector growth target; must be on the same basis as GDP. | N20: INSBU TRE, current prices (TRE COURANT yyyy.xls)
A21: VAAGR_KP | B21: A. National accounts | C21: Value added: agriculture, forestry, fishing (ISIC A) | D21: constant | E21: BIF billions, base-year prices | F21: 3459.6 | G21: 3556.6 | H21: 3517.1 | I21: 3600 | J21: 3483.9 | K21: 3641.8 | L21: ISTEEBU rebased national accounts (the series behind the WDI rebased GDP), or IMF staff report CR 26/150 statistical tables. Use ONE source for every row in block A. | M21: Sector growth target; must be on the same basis as GDP. | N21: INSBU TRE, previous-year prices (TRE CONSTANT yyyy.xls), chain-linked to 2019 prices
A22: VAIND_CP | B22: A. National accounts | C22: Value added: industry (ISIC B-F) | D22: current | E22: BIF billions | F22: 1392.5 | G22: 1417.7 | H22: 1641 | I22: 1880.2 | J22: 2279.6 | K22: 3287.1 | L22: ISTEEBU rebased national accounts (the series behind the WDI rebased GDP), or IMF staff report CR 26/150 statistical tables. Use ONE source for every row in block A. | M22: Sector growth target. | N22: INSBU TRE, current prices (TRE COURANT yyyy.xls) | O22: ISIC B-F: extraction, manufacturing, electricity, water, construction.
A23: VAIND_KP | B23: A. National accounts | C23: Value added: industry (ISIC B-F) | D23: constant | E23: BIF billions, base-year prices | F23: 1392.5 | G23: 1357.6 | H23: 1423.7 | I23: 1452.3 | J23: 1477.4 | K23: 1548 | L23: ISTEEBU rebased national accounts (the series behind the WDI rebased GDP), or IMF staff report CR 26/150 statistical tables. Use ONE source for every row in block A. | M23: Sector growth target. | N23: INSBU TRE, previous-year prices (TRE CONSTANT yyyy.xls), chain-linked to 2019 prices | O23: ISIC B-F: extraction, manufacturing, electricity, water, construction.
A24: VAMAN_CP | B24: A. National accounts | C24: of which: manufacturing (ISIC C) | D24: current | E24: BIF billions | F24: 953.5 | G24: 1014.8 | H24: 1089.8 | I24: 1293.4 | J24: 1561.5 | K24: 1826.5 | L24: ISTEEBU rebased national accounts (the series behind the WDI rebased GDP), or IMF staff report CR 26/150 statistical tables. Use ONE source for every row in block A. | M24: Separates factory supply shocks from mining and construction. | N24: INSBU TRE, current prices (TRE COURANT yyyy.xls)
A25: VAMAN_KP | B25: A. National accounts | C25: of which: manufacturing (ISIC C) | D25: constant | E25: BIF billions, base-year prices | F25: 953.5 | G25: 957.5 | H25: 991.7 | I25: 1001.7 | J25: 1069.2 | K25: 994.7 | L25: ISTEEBU rebased national accounts (the series behind the WDI rebased GDP), or IMF staff report CR 26/150 statistical tables. Use ONE source for every row in block A. | M25: Separates factory supply shocks from mining and construction. | N25: INSBU TRE, previous-year prices (TRE CONSTANT yyyy.xls), chain-linked to 2019 prices
A26: VASRV_CP | B26: A. National accounts | C26: Value added: services (ISIC G-U) | D26: current | E26: BIF billions | F26: 3740 | G26: 3866.3 | H26: 4162.9 | I26: 4765.4 | J26: 5632 | K26: 7328.3 | L26: ISTEEBU rebased national accounts (the series behind the WDI rebased GDP), or IMF staff report CR 26/150 statistical tables. Use ONE source for every row in block A. | M26: Sector growth target. | N26: INSBU TRE, current prices (TRE COURANT yyyy.xls) | O26: ISIC G-U, including U32 'Correction territoriale' (1.5% of VA in 2019).
A27: VASRV_KP | B27: A. National accounts | C27: Value added: services (ISIC G-U) | D27: constant | E27: BIF billions, base-year prices | F27: 3740 | G27: 3669.8 | H27: 3793.4 | I27: 3794.6 | J27: 4075.4 | K27: 4264.1 | L27: ISTEEBU rebased national accounts (the series behind the WDI rebased GDP), or IMF staff report CR 26/150 statistical tables. Use ONE source for every row in block A. | M27: Sector growth target. | N27: INSBU TRE, previous-year prices (TRE CONSTANT yyyy.xls), chain-linked to 2019 prices | O27: ISIC G-U, including U32 'Correction territoriale' (1.5% of VA in 2019).
A28: FXOFF | B28: B. FX at official rate | C28: Imports paid with FX sold at the OFFICIAL rate (BRB allocations), total | D28: - | E28: USD millions | L28: BRB (annual report / balance-of-payments or FX allocation statistics), or IMF staff report CR 23/270 and CR 26/150. | M28: The model assumes only fuel and chemicals are paid at the official rate, fixed at 2019 shares. The IMF says access changed after 2022. | O28: Not in the INSBU files: needs BRB data.
A29: FXOFFF | B29: B. FX at official rate | C29: of which: petroleum products | D29: - | E29: USD millions | L29: BRB (annual report / balance-of-payments or FX allocation statistics), or IMF staff report CR 23/270 and CR 26/150. | M29: Splits fuel from other official-rate imports. | O29: Not in the INSBU files: needs BRB data.

Sheet Checks
A1: Computed from sheet 'Data'. Do not edit. Blank until the inputs are filled.
A3: Check | B3: Formula | C3: 2019 | D3: 2020 | E3: 2021 | F3: 2022 | G3: 2023 | H3: 2024
A4: Deflator, GDP (base year = 100) | B4: 100 x current / constant | C4: =IF(AND(ISNUMBER(Data!F6),ISNUMBER(Data!F7)),100*Data!F6/Data!F7,"") | D4: =IF(AND(ISNUMBER(Data!G6),ISNUMBER(Data!G7)),100*Data!G6/Data!G7,"") | E4: =IF(AND(ISNUMBER(Data!H6),ISNUMBER(Data!H7)),100*Data!H6/Data!H7,"") | F4: =IF(AND(ISNUMBER(Data!I6),ISNUMBER(Data!I7)),100*Data!I6/Data!I7,"") | G4: =IF(AND(ISNUMBER(Data!J6),ISNUMBER(Data!J7)),100*Data!J6/Data!J7,"") | H4: =IF(AND(ISNUMBER(Data!K6),ISNUMBER(Data!K7)),100*Data!K6/Data!K7,"")
A5: Deflator, private consumption (base year = 100) | B5: 100 x current / constant | C5: =IF(AND(ISNUMBER(Data!F8),ISNUMBER(Data!F9)),100*Data!F8/Data!F9,"") | D5: =IF(AND(ISNUMBER(Data!G8),ISNUMBER(Data!G9)),100*Data!G8/Data!G9,"") | E5: =IF(AND(ISNUMBER(Data!H8),ISNUMBER(Data!H9)),100*Data!H8/Data!H9,"") | F5: =IF(AND(ISNUMBER(Data!I8),ISNUMBER(Data!I9)),100*Data!I8/Data!I9,"") | G5: =IF(AND(ISNUMBER(Data!J8),ISNUMBER(Data!J9)),100*Data!J8/Data!J9,"") | H5: =IF(AND(ISNUMBER(Data!K8),ISNUMBER(Data!K9)),100*Data!K8/Data!K9,"")
A6: Deflator, government consumption (base year = 100) | B6: 100 x current / constant | C6: =IF(AND(ISNUMBER(Data!F10),ISNUMBER(Data!F11)),100*Data!F10/Data!F11,"") | D6: =IF(AND(ISNUMBER(Data!G10),ISNUMBER(Data!G11)),100*Data!G10/Data!G11,"") | E6: =IF(AND(ISNUMBER(Data!H10),ISNUMBER(Data!H11)),100*Data!H10/Data!H11,"") | F6: =IF(AND(ISNUMBER(Data!I10),ISNUMBER(Data!I11)),100*Data!I10/Data!I11,"") | G6: =IF(AND(ISNUMBER(Data!J10),ISNUMBER(Data!J11)),100*Data!J10/Data!J11,"") | H6: =IF(AND(ISNUMBER(Data!K10),ISNUMBER(Data!K11)),100*Data!K10/Data!K11,"")
A7: Deflator, GFCF (base year = 100) | B7: 100 x current / constant | C7: =IF(AND(ISNUMBER(Data!F12),ISNUMBER(Data!F13)),100*Data!F12/Data!F13,"") | D7: =IF(AND(ISNUMBER(Data!G12),ISNUMBER(Data!G13)),100*Data!G12/Data!G13,"") | E7: =IF(AND(ISNUMBER(Data!H12),ISNUMBER(Data!H13)),100*Data!H12/Data!H13,"") | F7: =IF(AND(ISNUMBER(Data!I12),ISNUMBER(Data!I13)),100*Data!I12/Data!I13,"") | G7: =IF(AND(ISNUMBER(Data!J12),ISNUMBER(Data!J13)),100*Data!J12/Data!J13,"") | H7: =IF(AND(ISNUMBER(Data!K12),ISNUMBER(Data!K13)),100*Data!K12/Data!K13,"")
A8: Deflator, exports (base year = 100) | B8: 100 x current / constant | C8: =IF(AND(ISNUMBER(Data!F16),ISNUMBER(Data!F17)),100*Data!F16/Data!F17,"") | D8: =IF(AND(ISNUMBER(Data!G16),ISNUMBER(Data!G17)),100*Data!G16/Data!G17,"") | E8: =IF(AND(ISNUMBER(Data!H16),ISNUMBER(Data!H17)),100*Data!H16/Data!H17,"") | F8: =IF(AND(ISNUMBER(Data!I16),ISNUMBER(Data!I17)),100*Data!I16/Data!I17,"") | G8: =IF(AND(ISNUMBER(Data!J16),ISNUMBER(Data!J17)),100*Data!J16/Data!J17,"") | H8: =IF(AND(ISNUMBER(Data!K16),ISNUMBER(Data!K17)),100*Data!K16/Data!K17,"")
A9: Deflator, imports (base year = 100) | B9: 100 x current / constant | C9: =IF(AND(ISNUMBER(Data!F18),ISNUMBER(Data!F19)),100*Data!F18/Data!F19,"") | D9: =IF(AND(ISNUMBER(Data!G18),ISNUMBER(Data!G19)),100*Data!G18/Data!G19,"") | E9: =IF(AND(ISNUMBER(Data!H18),ISNUMBER(Data!H19)),100*Data!H18/Data!H19,"") | F9: =IF(AND(ISNUMBER(Data!I18),ISNUMBER(Data!I19)),100*Data!I18/Data!I19,"") | G9: =IF(AND(ISNUMBER(Data!J18),ISNUMBER(Data!J19)),100*Data!J18/Data!J19,"") | H9: =IF(AND(ISNUMBER(Data!K18),ISNUMBER(Data!K19)),100*Data!K18/Data!K19,"")
A10: Deflator, agriculture VA (base year = 100) | B10: 100 x current / constant | C10: =IF(AND(ISNUMBER(Data!F20),ISNUMBER(Data!F21)),100*Data!F20/Data!F21,"") | D10: =IF(AND(ISNUMBER(Data!G20),ISNUMBER(Data!G21)),100*Data!G20/Data!G21,"") | E10: =IF(AND(ISNUMBER(Data!H20),ISNUMBER(Data!H21)),100*Data!H20/Data!H21,"") | F10: =IF(AND(ISNUMBER(Data!I20),ISNUMBER(Data!I21)),100*Data!I20/Data!I21,"") | G10: =IF(AND(ISNUMBER(Data!J20),ISNUMBER(Data!J21)),100*Data!J20/Data!J21,"") | H10: =IF(AND(ISNUMBER(Data!K20),ISNUMBER(Data!K21)),100*Data!K20/Data!K21,"")
A11: Deflator, industry VA (base year = 100) | B11: 100 x current / constant | C11: =IF(AND(ISNUMBER(Data!F22),ISNUMBER(Data!F23)),100*Data!F22/Data!F23,"") | D11: =IF(AND(ISNUMBER(Data!G22),ISNUMBER(Data!G23)),100*Data!G22/Data!G23,"") | E11: =IF(AND(ISNUMBER(Data!H22),ISNUMBER(Data!H23)),100*Data!H22/Data!H23,"") | F11: =IF(AND(ISNUMBER(Data!I22),ISNUMBER(Data!I23)),100*Data!I22/Data!I23,"") | G11: =IF(AND(ISNUMBER(Data!J22),ISNUMBER(Data!J23)),100*Data!J22/Data!J23,"") | H11: =IF(AND(ISNUMBER(Data!K22),ISNUMBER(Data!K23)),100*Data!K22/Data!K23,"")
A12: Deflator, services VA (base year = 100) | B12: 100 x current / constant | C12: =IF(AND(ISNUMBER(Data!F26),ISNUMBER(Data!F27)),100*Data!F26/Data!F27,"") | D12: =IF(AND(ISNUMBER(Data!G26),ISNUMBER(Data!G27)),100*Data!G26/Data!G27,"") | E12: =IF(AND(ISNUMBER(Data!H26),ISNUMBER(Data!H27)),100*Data!H26/Data!H27,"") | F12: =IF(AND(ISNUMBER(Data!I26),ISNUMBER(Data!I27)),100*Data!I26/Data!I27,"") | G12: =IF(AND(ISNUMBER(Data!J26),ISNUMBER(Data!J27)),100*Data!J26/Data!J27,"") | H12: =IF(AND(ISNUMBER(Data!K26),ISNUMBER(Data!K27)),100*Data!K26/Data!K27,"")
A13: Growth, real GDP (%) | B13: constant prices, year on year | D13: =IF(AND(ISNUMBER(Data!G7),ISNUMBER(Data!F7)),100*(Data!G7/Data!F7-1),"") | E13: =IF(AND(ISNUMBER(Data!H7),ISNUMBER(Data!G7)),100*(Data!H7/Data!G7-1),"") | F13: =IF(AND(ISNUMBER(Data!I7),ISNUMBER(Data!H7)),100*(Data!I7/Data!H7-1),"") | G13: =IF(AND(ISNUMBER(Data!J7),ISNUMBER(Data!I7)),100*(Data!J7/Data!I7-1),"") | H13: =IF(AND(ISNUMBER(Data!K7),ISNUMBER(Data!J7)),100*(Data!K7/Data!J7-1),"")
A14: Growth, real agriculture VA (%) | B14: constant prices, year on year | D14: =IF(AND(ISNUMBER(Data!G21),ISNUMBER(Data!F21)),100*(Data!G21/Data!F21-1),"") | E14: =IF(AND(ISNUMBER(Data!H21),ISNUMBER(Data!G21)),100*(Data!H21/Data!G21-1),"") | F14: =IF(AND(ISNUMBER(Data!I21),ISNUMBER(Data!H21)),100*(Data!I21/Data!H21-1),"") | G14: =IF(AND(ISNUMBER(Data!J21),ISNUMBER(Data!I21)),100*(Data!J21/Data!I21-1),"") | H14: =IF(AND(ISNUMBER(Data!K21),ISNUMBER(Data!J21)),100*(Data!K21/Data!J21-1),"")
A15: Growth, real industry VA (%) | B15: constant prices, year on year | D15: =IF(AND(ISNUMBER(Data!G23),ISNUMBER(Data!F23)),100*(Data!G23/Data!F23-1),"") | E15: =IF(AND(ISNUMBER(Data!H23),ISNUMBER(Data!G23)),100*(Data!H23/Data!G23-1),"") | F15: =IF(AND(ISNUMBER(Data!I23),ISNUMBER(Data!H23)),100*(Data!I23/Data!H23-1),"") | G15: =IF(AND(ISNUMBER(Data!J23),ISNUMBER(Data!I23)),100*(Data!J23/Data!I23-1),"") | H15: =IF(AND(ISNUMBER(Data!K23),ISNUMBER(Data!J23)),100*(Data!K23/Data!J23-1),"")
A16: Growth, real manufacturing VA (%) | B16: constant prices, year on year | D16: =IF(AND(ISNUMBER(Data!G25),ISNUMBER(Data!F25)),100*(Data!G25/Data!F25-1),"") | E16: =IF(AND(ISNUMBER(Data!H25),ISNUMBER(Data!G25)),100*(Data!H25/Data!G25-1),"") | F16: =IF(AND(ISNUMBER(Data!I25),ISNUMBER(Data!H25)),100*(Data!I25/Data!H25-1),"") | G16: =IF(AND(ISNUMBER(Data!J25),ISNUMBER(Data!I25)),100*(Data!J25/Data!I25-1),"") | H16: =IF(AND(ISNUMBER(Data!K25),ISNUMBER(Data!J25)),100*(Data!K25/Data!J25-1),"")
A17: Growth, real services VA (%) | B17: constant prices, year on year | D17: =IF(AND(ISNUMBER(Data!G27),ISNUMBER(Data!F27)),100*(Data!G27/Data!F27-1),"") | E17: =IF(AND(ISNUMBER(Data!H27),ISNUMBER(Data!G27)),100*(Data!H27/Data!G27-1),"") | F17: =IF(AND(ISNUMBER(Data!I27),ISNUMBER(Data!H27)),100*(Data!I27/Data!H27-1),"") | G17: =IF(AND(ISNUMBER(Data!J27),ISNUMBER(Data!I27)),100*(Data!J27/Data!I27-1),"") | H17: =IF(AND(ISNUMBER(Data!K27),ISNUMBER(Data!J27)),100*(Data!K27/Data!J27-1),"")
A18: Growth, real private consumption (%) | B18: constant prices, year on year | D18: =IF(AND(ISNUMBER(Data!G9),ISNUMBER(Data!F9)),100*(Data!G9/Data!F9-1),"") | E18: =IF(AND(ISNUMBER(Data!H9),ISNUMBER(Data!G9)),100*(Data!H9/Data!G9-1),"") | F18: =IF(AND(ISNUMBER(Data!I9),ISNUMBER(Data!H9)),100*(Data!I9/Data!H9-1),"") | G18: =IF(AND(ISNUMBER(Data!J9),ISNUMBER(Data!I9)),100*(Data!J9/Data!I9-1),"") | H18: =IF(AND(ISNUMBER(Data!K9),ISNUMBER(Data!J9)),100*(Data!K9/Data!J9-1),"")
A19: Growth, real government consumption (%) | B19: constant prices, year on year | D19: =IF(AND(ISNUMBER(Data!G11),ISNUMBER(Data!F11)),100*(Data!G11/Data!F11-1),"") | E19: =IF(AND(ISNUMBER(Data!H11),ISNUMBER(Data!G11)),100*(Data!H11/Data!G11-1),"") | F19: =IF(AND(ISNUMBER(Data!I11),ISNUMBER(Data!H11)),100*(Data!I11/Data!H11-1),"") | G19: =IF(AND(ISNUMBER(Data!J11),ISNUMBER(Data!I11)),100*(Data!J11/Data!I11-1),"") | H19: =IF(AND(ISNUMBER(Data!K11),ISNUMBER(Data!J11)),100*(Data!K11/Data!J11-1),"")
A20: Growth, real GFCF (%) | B20: constant prices, year on year | D20: =IF(AND(ISNUMBER(Data!G13),ISNUMBER(Data!F13)),100*(Data!G13/Data!F13-1),"") | E20: =IF(AND(ISNUMBER(Data!H13),ISNUMBER(Data!G13)),100*(Data!H13/Data!G13-1),"") | F20: =IF(AND(ISNUMBER(Data!I13),ISNUMBER(Data!H13)),100*(Data!I13/Data!H13-1),"") | G20: =IF(AND(ISNUMBER(Data!J13),ISNUMBER(Data!I13)),100*(Data!J13/Data!I13-1),"") | H20: =IF(AND(ISNUMBER(Data!K13),ISNUMBER(Data!J13)),100*(Data!K13/Data!J13-1),"")
A21: Growth, real exports (%) | B21: constant prices, year on year | D21: =IF(AND(ISNUMBER(Data!G17),ISNUMBER(Data!F17)),100*(Data!G17/Data!F17-1),"") | E21: =IF(AND(ISNUMBER(Data!H17),ISNUMBER(Data!G17)),100*(Data!H17/Data!G17-1),"") | F21: =IF(AND(ISNUMBER(Data!I17),ISNUMBER(Data!H17)),100*(Data!I17/Data!H17-1),"") | G21: =IF(AND(ISNUMBER(Data!J17),ISNUMBER(Data!I17)),100*(Data!J17/Data!I17-1),"") | H21: =IF(AND(ISNUMBER(Data!K17),ISNUMBER(Data!J17)),100*(Data!K17/Data!J17-1),"")
A22: Growth, real imports (%) | B22: constant prices, year on year | D22: =IF(AND(ISNUMBER(Data!G19),ISNUMBER(Data!F19)),100*(Data!G19/Data!F19-1),"") | E22: =IF(AND(ISNUMBER(Data!H19),ISNUMBER(Data!G19)),100*(Data!H19/Data!G19-1),"") | F22: =IF(AND(ISNUMBER(Data!I19),ISNUMBER(Data!H19)),100*(Data!I19/Data!H19-1),"") | G22: =IF(AND(ISNUMBER(Data!J19),ISNUMBER(Data!I19)),100*(Data!J19/Data!I19-1),"") | H22: =IF(AND(ISNUMBER(Data!K19),ISNUMBER(Data!J19)),100*(Data!K19/Data!J19-1),"")
A23: Share of GDP, private consumption (%) | B23: current prices | C23: =IF(AND(ISNUMBER(Data!F8),ISNUMBER(Data!F6)),100*Data!F8/Data!F6,"") | D23: =IF(AND(ISNUMBER(Data!G8),ISNUMBER(Data!G6)),100*Data!G8/Data!G6,"") | E23: =IF(AND(ISNUMBER(Data!H8),ISNUMBER(Data!H6)),100*Data!H8/Data!H6,"") | F23: =IF(AND(ISNUMBER(Data!I8),ISNUMBER(Data!I6)),100*Data!I8/Data!I6,"") | G23: =IF(AND(ISNUMBER(Data!J8),ISNUMBER(Data!J6)),100*Data!J8/Data!J6,"") | H23: =IF(AND(ISNUMBER(Data!K8),ISNUMBER(Data!K6)),100*Data!K8/Data!K6,"")
A24: Share of GDP, government consumption (%) | B24: current prices | C24: =IF(AND(ISNUMBER(Data!F10),ISNUMBER(Data!F6)),100*Data!F10/Data!F6,"") | D24: =IF(AND(ISNUMBER(Data!G10),ISNUMBER(Data!G6)),100*Data!G10/Data!G6,"") | E24: =IF(AND(ISNUMBER(Data!H10),ISNUMBER(Data!H6)),100*Data!H10/Data!H6,"") | F24: =IF(AND(ISNUMBER(Data!I10),ISNUMBER(Data!I6)),100*Data!I10/Data!I6,"") | G24: =IF(AND(ISNUMBER(Data!J10),ISNUMBER(Data!J6)),100*Data!J10/Data!J6,"") | H24: =IF(AND(ISNUMBER(Data!K10),ISNUMBER(Data!K6)),100*Data!K10/Data!K6,"")
A25: Share of GDP, GFCF (%) | B25: current prices | C25: =IF(AND(ISNUMBER(Data!F12),ISNUMBER(Data!F6)),100*Data!F12/Data!F6,"") | D25: =IF(AND(ISNUMBER(Data!G12),ISNUMBER(Data!G6)),100*Data!G12/Data!G6,"") | E25: =IF(AND(ISNUMBER(Data!H12),ISNUMBER(Data!H6)),100*Data!H12/Data!H6,"") | F25: =IF(AND(ISNUMBER(Data!I12),ISNUMBER(Data!I6)),100*Data!I12/Data!I6,"") | G25: =IF(AND(ISNUMBER(Data!J12),ISNUMBER(Data!J6)),100*Data!J12/Data!J6,"") | H25: =IF(AND(ISNUMBER(Data!K12),ISNUMBER(Data!K6)),100*Data!K12/Data!K6,"")
A26: Share of GDP, exports (%) | B26: current prices | C26: =IF(AND(ISNUMBER(Data!F16),ISNUMBER(Data!F6)),100*Data!F16/Data!F6,"") | D26: =IF(AND(ISNUMBER(Data!G16),ISNUMBER(Data!G6)),100*Data!G16/Data!G6,"") | E26: =IF(AND(ISNUMBER(Data!H16),ISNUMBER(Data!H6)),100*Data!H16/Data!H6,"") | F26: =IF(AND(ISNUMBER(Data!I16),ISNUMBER(Data!I6)),100*Data!I16/Data!I6,"") | G26: =IF(AND(ISNUMBER(Data!J16),ISNUMBER(Data!J6)),100*Data!J16/Data!J6,"") | H26: =IF(AND(ISNUMBER(Data!K16),ISNUMBER(Data!K6)),100*Data!K16/Data!K6,"")
A27: Share of GDP, imports (%) | B27: current prices | C27: =IF(AND(ISNUMBER(Data!F18),ISNUMBER(Data!F6)),100*Data!F18/Data!F6,"") | D27: =IF(AND(ISNUMBER(Data!G18),ISNUMBER(Data!G6)),100*Data!G18/Data!G6,"") | E27: =IF(AND(ISNUMBER(Data!H18),ISNUMBER(Data!H6)),100*Data!H18/Data!H6,"") | F27: =IF(AND(ISNUMBER(Data!I18),ISNUMBER(Data!I6)),100*Data!I18/Data!I6,"") | G27: =IF(AND(ISNUMBER(Data!J18),ISNUMBER(Data!J6)),100*Data!J18/Data!J6,"") | H27: =IF(AND(ISNUMBER(Data!K18),ISNUMBER(Data!K6)),100*Data!K18/Data!K6,"")
A28: GDP identity residual, current (% of GDP) | B28: GDP - C - G - GFCF - X + M; = stocks + discrepancy, should be small | C28: =IF(AND(ISNUMBER(Data!F6),ISNUMBER(Data!F8),ISNUMBER(Data!F10),ISNUMBER(Data!F12),ISNUMBER(Data!F16),ISNUMBER(Data!F18)),100*(Data!F6-Data!F8-Data!F10-Data!F12-Data!F16+Data!F18)/Data!F6,"") | D28: =IF(AND(ISNUMBER(Data!G6),ISNUMBER(Data!G8),ISNUMBER(Data!G10),ISNUMBER(Data!G12),ISNUMBER(Data!G16),ISNUMBER(Data!G18)),100*(Data!G6-Data!G8-Data!G10-Data!G12-Data!G16+Data!G18)/Data!G6,"") | E28: =IF(AND(ISNUMBER(Data!H6),ISNUMBER(Data!H8),ISNUMBER(Data!H10),ISNUMBER(Data!H12),ISNUMBER(Data!H16),ISNUMBER(Data!H18)),100*(Data!H6-Data!H8-Data!H10-Data!H12-Data!H16+Data!H18)/Data!H6,"") | F28: =IF(AND(ISNUMBER(Data!I6),ISNUMBER(Data!I8),ISNUMBER(Data!I10),ISNUMBER(Data!I12),ISNUMBER(Data!I16),ISNUMBER(Data!I18)),100*(Data!I6-Data!I8-Data!I10-Data!I12-Data!I16+Data!I18)/Data!I6,"") | G28: =IF(AND(ISNUMBER(Data!J6),ISNUMBER(Data!J8),ISNUMBER(Data!J10),ISNUMBER(Data!J12),ISNUMBER(Data!J16),ISNUMBER(Data!J18)),100*(Data!J6-Data!J8-Data!J10-Data!J12-Data!J16+Data!J18)/Data!J6,"") | H28: =IF(AND(ISNUMBER(Data!K6),ISNUMBER(Data!K8),ISNUMBER(Data!K10),ISNUMBER(Data!K12),ISNUMBER(Data!K16),ISNUMBER(Data!K18)),100*(Data!K6-Data!K8-Data!K10-Data!K12-Data!K16+Data!K18)/Data!K6,"")
A29: Sector VA as % of GDP, current | B29: (agriculture + industry + services) / GDP; the rest is net taxes | C29: =IF(AND(ISNUMBER(Data!F20),ISNUMBER(Data!F22),ISNUMBER(Data!F26),ISNUMBER(Data!F6)),100*(Data!F20+Data!F22+Data!F26)/Data!F6,"") | D29: =IF(AND(ISNUMBER(Data!G20),ISNUMBER(Data!G22),ISNUMBER(Data!G26),ISNUMBER(Data!G6)),100*(Data!G20+Data!G22+Data!G26)/Data!G6,"") | E29: =IF(AND(ISNUMBER(Data!H20),ISNUMBER(Data!H22),ISNUMBER(Data!H26),ISNUMBER(Data!H6)),100*(Data!H20+Data!H22+Data!H26)/Data!H6,"") | F29: =IF(AND(ISNUMBER(Data!I20),ISNUMBER(Data!I22),ISNUMBER(Data!I26),ISNUMBER(Data!I6)),100*(Data!I20+Data!I22+Data!I26)/Data!I6,"") | G29: =IF(AND(ISNUMBER(Data!J20),ISNUMBER(Data!J22),ISNUMBER(Data!J26),ISNUMBER(Data!J6)),100*(Data!J20+Data!J22+Data!J26)/Data!J6,"") | H29: =IF(AND(ISNUMBER(Data!K20),ISNUMBER(Data!K22),ISNUMBER(Data!K26),ISNUMBER(Data!K6)),100*(Data!K20+Data!K22+Data!K26)/Data!K6,"")
A30: Petroleum share of official-rate FX (%) | B30: FXOFFF / FXOFF | C30: =IF(AND(ISNUMBER(Data!F29),ISNUMBER(Data!F28)),100*Data!F29/Data!F28,"") | D30: =IF(AND(ISNUMBER(Data!G29),ISNUMBER(Data!G28)),100*Data!G29/Data!G28,"") | E30: =IF(AND(ISNUMBER(Data!H29),ISNUMBER(Data!H28)),100*Data!H29/Data!H28,"") | F30: =IF(AND(ISNUMBER(Data!I29),ISNUMBER(Data!I28)),100*Data!I29/Data!I28,"") | G30: =IF(AND(ISNUMBER(Data!J29),ISNUMBER(Data!J28)),100*Data!J29/Data!J28,"") | H30: =IF(AND(ISNUMBER(Data!K29),ISNUMBER(Data!K28)),100*Data!K29/Data!K28,"")
